CHANGES.rst
LICENSE
MANIFEST.in
README.rst
setup.py
collective/__init__.py
collective.js.fancytree.egg-info/PKG-INFO
collective.js.fancytree.egg-info/SOURCES.txt
collective.js.fancytree.egg-info/dependency_links.txt
collective.js.fancytree.egg-info/namespace_packages.txt
collective.js.fancytree.egg-info/not-zip-safe
collective.js.fancytree.egg-info/requires.txt
collective.js.fancytree.egg-info/top_level.txt
collective/js/__init__.py
collective/js/fancytree/__init__.py
collective/js/fancytree/configure.zcml
collective/js/fancytree/upgrades.py
collective/js/fancytree/profiles/all/jsregistry.xml
collective/js/fancytree/profiles/all/metadata.xml
collective/js/fancytree/profiles/default/jsregistry.xml
collective/js/fancytree/profiles/default/metadata.xml
collective/js/fancytree/profiles/theme-lion/cssregistry.xml
collective/js/fancytree/profiles/theme-vista/cssregistry.xml
collective/js/fancytree/resources/jquery.fancytree-all.js
collective/js/fancytree/resources/jquery.fancytree-all.min.js
collective/js/fancytree/resources/jquery.fancytree.js
collective/js/fancytree/resources/jquery.fancytree.min.js
collective/js/fancytree/resources/theme-lion/icons.gif
collective/js/fancytree/resources/theme-lion/loading.gif
collective/js/fancytree/resources/theme-lion/ui.fancytree.css
collective/js/fancytree/resources/theme-lion/vline.gif
collective/js/fancytree/resources/theme-vista/icons.gif
collective/js/fancytree/resources/theme-vista/loading.gif
collective/js/fancytree/resources/theme-vista/ui.fancytree.css
collective/js/fancytree/resources/theme-vista/vline.gif