Metadata-Version: 1.1
Name: collective.js.fancytree
Version: 2.19.0.0
Summary: Fancytree as a zope resource
Home-page: https://github.com/imio/
Author: IMIO
Author-email: support@imio.be
License: gpl
Platform: UNKNOWN
Classifier: Environment :: Web Environment
Classifier: Programming Language :: Python
Classifier: Programming Language :: Python :: 2.7
Classifier: Framework :: Plone
Classifier: Framework :: Plone :: 4.2
Classifier: Framework :: Plone :: 4.3
